gemini_profanity_filter/__init__.py
gemini_profanity_filter/profanity_filter.py
gemini_profanity_filter-1.2.0.dist-info/LICENSE
gemini_profanity_filter-1.2.0.dist-info/METADATA
gemini_profanity_filter-1.2.0.dist-info/WHEEL
gemini_profanity_filter-1.2.0.dist-info/top_level.txt
gemini_profanity_filter-1.2.0.dist-info/RECORD
