Metadata-Version: 2.1
Name: gemini-profanity-filter
Version: 1.2.0
Summary: A Python module for detecting and filtering profanity using Google's Gemini API
Author: Mark
Author-email: firi8228@gmail.com
Classifier: Programming Language :: Python :: 3
Classifier: License :: OSI Approved :: MIT License
Classifier: Operating System :: OS Independent
Requires-Python: >=3.7
License-File: LICENSE
Requires-Dist: google-generativeai >=0.3.0
